irbis/__init__.py
irbis/_common.py
irbis/abstract.py
irbis/alphabet.py
irbis/builder.py
irbis/connection.py
irbis/database.py
irbis/direct.py
irbis/error.py
irbis/export.py
irbis/ini.py
irbis/menus.py
irbis/opt.py
irbis/par.py
irbis/process.py
irbis/query.py
irbis/resource.py
irbis/response.py
irbis/saveable.py
irbis/search.py
irbis/specification.py
irbis/stats.py
irbis/table.py
irbis/terms.py
irbis/tree.py
irbis/user.py
irbis/version.py
irbis/records/__init__.py
irbis/records/abstract.py
irbis/records/field.py
irbis/records/raw_record.py
irbis/records/record.py
irbis/records/subfield.py
irbis-0.2.376.dist-info/LICENSE
irbis-0.2.376.dist-info/METADATA
irbis-0.2.376.dist-info/WHEEL
irbis-0.2.376.dist-info/top_level.txt
irbis-0.2.376.dist-info/RECORD
