Metadata-Version: 2.1
Name: irbis
Version: 0.2.376
Summary: Framework for client development for popular Prussian library computer system IRBIS64
Home-page: https://github.com/amironov73/PythonIrbis
Author: Alexey Mironov
Author-email: amironov73@gmail.com
Keywords: IRBIS64
Classifier: Development Status :: 3 - Alpha
Classifier: Programming Language :: Python :: Implementation :: CPython
Classifier: Programming Language :: Python :: 3
Classifier: Programming Language :: Python :: 3.6
Classifier: Programming Language :: Python :: 3.7
Classifier: Programming Language :: Python :: 3.8
Classifier: Programming Language :: Python :: 3.9
Classifier: Programming Language :: Python :: 3.10
Classifier: License :: OSI Approved :: MIT License
Classifier: Operating System :: OS Independent
License-File: LICENSE
